<?xml version="1.0"?>
<!DOCTYPE hibernate-mapping PUBLIC "-//Hibernate/Hibernate Mapping DTD 3.0//EN"
"http://hibernate.sourceforge.net/hibernate-mapping-3.0.dtd">
<!-- Generated Apr 6, 2013 8:03:56 AM by Hibernate Tools 4.0.0 -->
<hibernate-mapping>
    <class name="com.scoutin.entities.Album" table="album" catalog="Scoutin">
        <id name="albumId" type="java.lang.Long">
            <column name="ALBUM_ID" />
            <generator class="identity" />
        </id>
        <property name="accountId" type="int">
            <column name="ACCOUNT_ID" not-null="true" />
        </property>
        <property name="name" type="string">
            <column name="NAME" length="35" />
        </property>
        <property name="coverPath" type="string">
            <column name="COVER_PATH" />
        </property>
        <property name="createdTime" type="timestamp">
            <column name="CREATED_TIME" length="19" />
        </property>
        <property name="updatedTime" type="timestamp">
            <column name="UPDATED_TIME" length="19" />
        </property>
        <property name="followCount" type="java.lang.Integer">
            <column name="FOLLOW_COUNT" />
        </property>
    </class>
</hibernate-mapping>
